rtl/pe.v
module pe #(
    parameter DATA_WIDTH = 8
)(
    input wire clk,
    input wire rst,
    input wire load_weight,                       // 1 = Load/Freeze Weight, 0 = Compute
    input wire [DATA_WIDTH-1:0] weight_in,        // Weight data from left neighbor
    input wire [DATA_WIDTH-1:0] act_in,           // Activation data from top neighbor
    output reg [DATA_WIDTH-1:0] weight_out,       // Pass weight right
    output reg [DATA_WIDTH-1:0] act_out,          // Pass activation down
    output reg [(2*DATA_WIDTH)-1:0] accum         // 16-bit Accumulator to prevent overflow
);

    // Internal register to freeze the weight in place (Weight-Stationary)
    reg [DATA_WIDTH-1:0] stationary_weight;

    always @(posedge clk or posedge rst) begin
        if (rst) begin
            stationary_weight <= {DATA_WIDTH{1'b0}};
            weight_out        <= {DATA_WIDTH{1'b0}};
            act_out           <= {DATA_WIDTH{1'b0}};
            accum             <= {(2*DATA_WIDTH){1'b0}};
        end 
        else begin
            if (load_weight) begin
                stationary_weight <= weight_in;   // Phase 1: Lock the weight in memory
            end 
            else begin
                // Phase 2: Multiply incoming activation with stationary weight and accumulate
                accum <= accum + (act_in * stationary_weight);
            end
            
            // Pipelined data propagation: Pass inputs to neighbors on the next clock edge
            weight_out <= weight_in;
            act_out    <= act_in;
        end
    end
endmodule

rtl/systolic_array.v
module systolic_array #(
    parameter DATA_WIDTH = 8,
    parameter GRID_SIZE = 2 // Change to 4 for a 4x4 array
)(
    input wire clk,
    input wire rst,
    input wire load_weight,
    
    // Flat 1D arrays to interface with external pins/buses
    input wire [(GRID_SIZE * DATA_WIDTH)-1:0] weight_inputs, // Inputs to the left column
    input wire [(GRID_SIZE * DATA_WIDTH)-1:0] act_inputs,    // Inputs to the top row
    output wire [((GRID_SIZE * GRID_SIZE) * (2*DATA_WIDTH))-1:0] flattened_outputs
);

    // Create 2D wire matrices to interconnect internal PEs horizontally and vertically
    wire [DATA_WIDTH-1:0] horiz_wires [0:GRID_SIZE][0:GRID_SIZE];
    wire [DATA_WIDTH-1:0] vert_wires  [0:GRID_SIZE][0:GRID_SIZE];
    wire [(2*DATA_WIDTH)-1:0] pe_accum [0:GRID_SIZE-1][0:GRID_SIZE-1];

    // Unpack flat 1D inputs into the 2D wire network boundaries
    genvar b;
    generate
        for (b = 0; b < GRID_SIZE; b = b + 1) begin: input_bind
            assign horiz_wires[b][0] = weight_inputs[(b+1)*DATA_WIDTH-1 : b*DATA_WIDTH];
            assign vert_wires[0][b]  = act_inputs[(b+1)*DATA_WIDTH-1 : b*DATA_WIDTH];
        end
    endgenerate

    // Generate Loop Matrix to construct and wire the grid
    genvar i, j;
    generate
        for (i = 0; i < GRID_SIZE; i = i + 1) begin: row
            for (j = 0; j < GRID_SIZE; j = j + 1) begin: col
                pe #(.DATA_WIDTH(DATA_WIDTH)) PE_inst (
                    .clk(clk),
                    .rst(rst),
                    .load_weight(load_weight),
                    .weight_in(horiz_wires[i][j]),
                    .act_in(vert_wires[i][j]),
                    .weight_out(horiz_wires[i][j+1]),
                    .act_out(vert_wires[i+1][j]),
                    .accum(pe_accum[i][j])
                );
                
                // Pack 2D accumulation matrix back into a single flat output channel
                assign flattened_outputs[((i*GRID_SIZE+j)+1)*(2*DATA_WIDTH)-1 : (i*GRID_SIZE+j)*(2*DATA_WIDTH)] = pe_accum[i][j];
            end
        end
    endgenerate

endmodule

rtl/axi_interface.v
module axi_interface #(
    parameter DATA_WIDTH = 8,
    parameter GRID_SIZE = 2
)(
    // Global Clock and Active-Low Reset
    input wire S_AXI_ACLK,
    input wire S_AXI_ARESETN,

    // AXI4-Lite Write Address Channel
    input wire [31:0] S_AXI_AWADDR,
    input wire S_AXI_AWVALID,
    output reg S_AXI_AWREADY,

    // AXI4-Lite Write Data Channel
    input wire [31:0] S_AXI_WDATA,
    input wire S_AXI_WVALID,
    output reg S_AXI_WREADY,

    // AXI4-Lite Write Response Channel
    output reg [1:0] S_AXI_BRESP,
    output reg S_AXI_BVALID,
    input wire S_AXI_BREADY,

    // Outward-facing Control signals wired directly to the Systolic Array
    output reg [(GRID_SIZE * DATA_WIDTH)-1:0] weight_data_out,
    output reg [(GRID_SIZE * DATA_WIDTH)-1:0] act_data_out,
    output reg load_weight_control
);

    // FSM State Encoding
    localparam IDLE  = 2'b00,
               WRITE = 2'b01,
               RESP  = 2'b10;

    reg [1:0] current_state;

    // Handshake Control State Machine
    always @(posedge S_AXI_ACLK) begin
        if (!S_AXI_ARESETN) begin
            current_state       <= IDLE;
            S_AXI_AWREADY       <= 1'b0;
            S_AXI_WREADY        <= 1'b0;
            S_AXI_BVALID        <= 1'b0;
            S_AXI_BRESP         <= 2'b00;
            weight_data_out     <= 0;
            act_data_out        <= 0;
            load_weight_control <= 1'b0;
        end 
        else begin
            case (current_state)
                IDLE: begin
                    S_AXI_BVALID <= 1'b0;
                    // Wait for both Address and Data to be declared valid by the master CPU
                    if (S_AXI_AWVALID && S_AXI_WVALID) begin
                        S_AXI_AWREADY <= 1'b1; // Assert ready
                        S_AXI_WREADY  <= 1'b1; // Assert ready
                        current_state <= WRITE;
                    end
                end

                WRITE: begin
                    S_AXI_AWREADY <= 1'b0; // Clear handshake lines
                    S_AXI_WREADY  <= 1'b0;
                    
                    // Address Decoding Matrix
                    case (S_AXI_AWADDR)
                        32'h0000_0000: load_weight_control <= S_AXI_WDATA[0];   // Control Register (Bit 0 = Load signal)
                        32'h0000_0004: weight_data_out     <= S_AXI_WDATA[(GRID_SIZE*DATA_WIDTH)-1:0]; // Memory location for Weights
                        32'h0000_0008: act_data_out        <= S_AXI_WDATA[(GRID_SIZE*DATA_WIDTH)-1:0]; // Memory location for Activations
                    endcase
                    
                    S_AXI_BVALID <= 1'b1; // Assert that response status is ready
                    current_state <= RESP;
                end

                RESP: begin
                    if (S_AXI_BREADY) begin // Wait for master acknowledgment
                        S_AXI_BVALID  <= 1'b0;
                        current_state <= IDLE;
                    end
                end
                
                default: current_state <= IDLE;
            endcase
        end
    end
endmodule

sim/tb_systolic.sv
`timescale 1ns / 1ps

module tb_systolic();
    reg clk;
    reg rst_n;
    
    // AXI Bus Simulation Signals
    reg [31:0] awaddr;
    reg awvalid;
    wire awready;
    reg [31:0] wdata;
    reg wvalid;
    wire wready;
    wire bvalid;
    reg bready;

    wire [15:0] weight_stream;
    wire [15:0] act_stream;
    wire ctrl_load;
    wire [63:0] results; // Holds four 16-bit outputs from the 2x2 grid

    // Instantiate AXI Interface Wrapper
    axi_interface #(.GRID_SIZE(2)) DUT_AXI (
        .S_AXI_ACLK(clk), .S_AXI_ARESETN(rst_n),
        .S_AXI_AWADDR(awaddr), .S_AXI_AWVALID(awvalid), .S_AXI_AWREADY(awready),
        .S_AXI_WDATA(wdata), .S_AXI_WVALID(wvalid), .S_AXI_WREADY(wready),
        .S_AXI_BVALID(bvalid), .S_AXI_BREADY(bready), .S_AXI_BRESP(),
        .weight_data_out(weight_stream), .act_data_out(act_stream), .load_weight_control(ctrl_load)
    );

    // Instantiate Compute Core
    systolic_array #(.GRID_SIZE(2)) DUT_ARRAY (
        .clk(clk), .rst(!rst_n), .load_weight(ctrl_load),
        .weight_inputs(weight_stream), .act_inputs(act_stream),
        .flattened_outputs(results)
    );

    // Generate 100MHz clock signal
    always #5 clk = ~clk;

    // Automated Icarus Verilog waveform logging block
    initial begin
        $dumpfile("dump.vcd");
        $dumpvars(0, tb_systolic);
    end

    initial begin
        // Initialize lines
        clk = 0; rst_n = 0; awaddr = 0; awvalid = 0; wdata = 0; wvalid = 0; bready = 1;
        #20 rst_n = 1; // Release reset
        #10;

        // Transaction 1: Turn ON load_weight control bit
        awaddr = 32'h0000_0000; wdata = 32'h0000_0001; awvalid = 1; wvalid = 1;
        @(posedge clk); while(!awready) @(posedge clk);
        #5 awvalid = 0; wvalid = 0; #20;

        // Transaction 2: Stream weights into memory space (Load weight vector Hex 04 and 02)
        awaddr = 32'h0000_0004; wdata = 32'h0000_0402; awvalid = 1; wvalid = 1;
        @(posedge clk); while(!awready) @(posedge clk);
        #5 awvalid = 0; wvalid = 0; #20;

        // Transaction 3: Turn OFF load_weight to lock them in place
        awaddr = 32'h0000_0000; wdata = 32'h0000_0000; awvalid = 1; wvalid = 1;
        @(posedge clk); while(!awready) @(posedge clk);
        #5 awvalid = 0; wvalid = 0; #20;

        // Transaction 4: Stream activations into computing channels (Inputs Hex 03 and 06)
        awaddr = 32'h0000_0008; wdata = 32'h0000_0306; awvalid = 1; wvalid = 1;
        @(posedge clk); while(!awready) @(posedge clk);
        #5 awvalid = 0; wvalid = 0; 
        
        // Wait 4 clock cycles for processing array pipeline calculation latency
        repeat(4) @(posedge clk);

        // Print final computations out directly to simulation terminal console
        $display("--- SIMULATION VERIFICATION OUTPUTS ---");
        $display("PE[0][0] Accumulation Result: %d", results[15:0]);
        $display("PE[0][1] Accumulation Result: %d", results[31:16]);
        $display("PE[1][0] Accumulation Result: %d", results[47:32]);
        $display("PE[1][1] Accumulation Result: %d", results[63:48]);
        $display("---------------------------------------");
        $finish;
    end
endmodule

sim/dump.vcd
$date
	Sun May 24 17:07:33 2026
$end
$version
	Icarus Verilog
$end
$timescale
	1ps
$end
$scope module tb_systolic $end
$var wire 1 ! wready $end
$var wire 16 " weight_stream [15:0] $end
$var wire 64 # results [63:0] $end
$var wire 1 $ ctrl_load $end
$var wire 1 % bvalid $end
$var wire 1 & awready $end
$var wire 16 ' act_stream [15:0] $end
$var reg 32 ( awaddr [31:0] $end
$var reg 1 ) awvalid $end
$var reg 1 * bready $end
$var reg 1 + clk $end
$var reg 1 , rst_n $end
$var reg 32 - wdata [31:0] $end
$var reg 1 . wvalid $end
$scope module DUT_ARRAY $end
$var wire 1 + clk $end
$var wire 1 / rst $end
$var wire 16 0 weight_inputs [15:0] $end
$var wire 1 $ load_weight $end
$var wire 64 1 flattened_outputs [63:0] $end
$var wire 16 2 act_inputs [15:0] $end
$var parameter 32 3 DATA_WIDTH $end
$var parameter 32 4 GRID_SIZE $end
$scope begin input_bind[0] $end
$var parameter 2 5 b $end
$upscope $end
$scope begin input_bind[1] $end
$var parameter 2 6 b $end
$upscope $end
$scope begin row[0] $end
$var parameter 2 7 i $end
$scope begin col[0] $end
$var parameter 2 8 j $end
$scope module PE_inst $end
$var wire 8 9 act_in [7:0] $end
$var wire 1 + clk $end
$var wire 1 / rst $end
$var wire 8 : weight_in [7:0] $end
$var wire 1 $ load_weight $end
$var parameter 32 ; DATA_WIDTH $end
$var reg 16 < accum [15:0] $end
$var reg 8 = act_out [7:0] $end
$var reg 8 > stationary_weight [7:0] $end
$var reg 8 ? weight_out [7:0] $end
$upscope $end
$upscope $end
$scope begin col[1] $end
$var parameter 2 @ j $end
$scope module PE_inst $end
$var wire 8 A act_in [7:0] $end
$var wire 1 + clk $end
$var wire 1 / rst $end
$var wire 8 B weight_in [7:0] $end
$var wire 1 $ load_weight $end
$var parameter 32 C DATA_WIDTH $end
$var reg 16 D accum [15:0] $end
$var reg 8 E act_out [7:0] $end
$var reg 8 F stationary_weight [7:0] $end
$var reg 8 G weight_out [7:0] $end
$upscope $end
$upscope $end
$upscope $end
$scope begin row[1] $end
$var parameter 2 H i $end
$scope begin col[0] $end
$var parameter 2 I j $end
$scope module PE_inst $end
$var wire 8 J act_in [7:0] $end
$var wire 1 + clk $end
$var wire 1 / rst $end
$var wire 8 K weight_in [7:0] $end
$var wire 1 $ load_weight $end
$var parameter 32 L DATA_WIDTH $end
$var reg 16 M accum [15:0] $end
$var reg 8 N act_out [7:0] $end
$var reg 8 O stationary_weight [7:0] $end
$var reg 8 P weight_out [7:0] $end
$upscope $end
$upscope $end
$scope begin col[1] $end
$var parameter 2 Q j $end
$scope module PE_inst $end
$var wire 8 R act_in [7:0] $end
$var wire 1 + clk $end
$var wire 1 / rst $end
$var wire 8 S weight_in [7:0] $end
$var wire 1 $ load_weight $end
$var parameter 32 T DATA_WIDTH $end
$var reg 16 U accum [15:0] $end
$var reg 8 V act_out [7:0] $end
$var reg 8 W stationary_weight [7:0] $end
$var reg 8 X weight_out [7:0] $end
$upscope $end
$upscope $end
$upscope $end
$upscope $end
$scope module DUT_AXI $end
$var wire 1 + S_AXI_ACLK $end
$var wire 1 , S_AXI_ARESETN $end
$var wire 32 Y S_AXI_AWADDR [31:0] $end
$var wire 1 ) S_AXI_AWVALID $end
$var wire 1 * S_AXI_BREADY $end
$var wire 32 Z S_AXI_WDATA [31:0] $end
$var wire 1 . S_AXI_WVALID $end
$var parameter 32 [ DATA_WIDTH $end
$var parameter 32 \ GRID_SIZE $end
$var parameter 2 ] IDLE $end
$var parameter 2 ^ RESP $end
$var parameter 2 _ WRITE $end
$var reg 1 & S_AXI_AWREADY $end
$var reg 2 ` S_AXI_BRESP [1:0] $end
$var reg 1 % S_AXI_BVALID $end
$var reg 1 ! S_AXI_WREADY $end
$var reg 16 a act_data_out [15:0] $end
$var reg 2 b current_state [1:0] $end
$var reg 1 $ load_weight_control $end
$var reg 16 c weight_data_out [15:0] $end
$upscope $end
$upscope $end
$enddefinitions $end
$comment Show the parameter values. $end
$dumpall
b1 _
b10 ^
b0 ]
b10 \
b1000 [
b1000 T
b1 Q
b1000 L
b0 I
b1 H
b1000 C
b1 @
b1000 ;
b0 8
b0 7
b1 6
b0 5
b10 4
b1000 3
$end
#0
$dumpvars
bx c
bx b
bx a
bx `
b0 Z
b0 Y
b0 X
b0 W
b0 V
b0 U
b0 S
b0 R
b0 P
b0 O
b0 N
b0 M
bx K
b0 J
b0 G
b0 F
b0 E
b0 D
b0 B
bx A
b0 ?
b0 >
b0 =
b0 <
bx :
bx 9
bx 2
b0 1
bx 0
1/
0.
b0 -
0,
0+
1*
0)
b0 (
bx '
x&
x%
x$
b0 #
bx "
x!
$end
#5000
b0 A
b0 9
b0 K
b0 :
0$
b0 '
b0 2
b0 a
b0 "
b0 0
b0 c
b0 `
0%
0!
0&
b0 b
1+
#10000
0+
#15000
1+
#20000
0+
0/
1,
#25000
1+
#30000
0+
1.
1)
b1 -
b1 Z
#35000
b1 b
1!
1&
1+
#40000
0+
#45000
b10 b
1%
1$
0!
0&
1+
#50000
0.
0)
0+
#55000
b0 b
0%
1+
#60000
0+
#65000
1+
#70000
0+
1.
1)
b10000000010 -
b10000000010 Z
b100 (
b100 Y
#75000
b1 b
1!
1&
1+
#80000
0+
#85000
b100 K
b10 :
b10 b
1%
b10000000010 "
b10000000010 0
b10000000010 c
0!
0&
1+
#90000
0.
0)
0+
#95000
b10 ?
b10 B
b10 >
b100 P
b100 S
b100 O
b0 b
0%
1+
#100000
0+
#105000
b100 X
b100 W
b10 G
b10 F
1+
#110000
0+
1.
1)
b0 -
b0 Z
b0 (
b0 Y
#115000
b1 b
1!
1&
1+
#120000
0+
#125000
b10 b
1%
0$
0!
0&
1+
#130000
0.
0)
0+
#135000
b0 b
0%
1+
#140000
0+
#145000
1+
#150000
0+
1.
1)
b1100000110 -
b1100000110 Z
b1000 (
b1000 Y
#155000
b1 b
1!
1&
1+
#160000
0+
#165000
b11 A
b110 9
b10 b
1%
b1100000110 '
b1100000110 2
b1100000110 a
0!
0&
1+
#170000
0.
0)
0+
#175000
b110 =
b110 J
b1100 <
b11 E
b11 R
b1100000000000001100 #
b1100000000000001100 1
b110 D
b0 b
0%
1+
#180000
0+
#185000
b11 V
b1100 U
b110 N
b11000 M
b1100 D
b1100000000000001100000000000000011000000000000011000 #
b1100000000000001100000000000000011000000000000011000 1
b11000 <
1+
#190000
0+
#195000
b100100 <
b10010 D
b110000 M
b11000000000000011000000000000000100100000000000100100 #
b11000000000000011000000000000000100100000000000100100 1
b11000 U
1+
#200000
0+
#205000
b100100 U
b1001000 M
b11000 D
b100100000000000100100000000000000110000000000000110000 #
b100100000000000100100000000000000110000000000000110000 1
b110000 <
1+
